week1_lab3/controller.v
module fsm_controller (
    input clk, rst,
    input start, last, do_add,      
    
    // ---- TASK B3: NEW DFT SCAN PORTS ----
    input scan_enable,              
    input [2:0] scan_in,            
    output reg [2:0] state,         
    
    // Functional control outputs driven to other modules
    output reg load, add_en, shift, count_en, clear, done 
);

    // Explicit Binary State Assignments
    localparam IDLE  = 3'b000, // 0
               LOAD  = 3'b001, // 1
               CHECK = 3'b010, // 2
               ADD   = 3'b011, // 3
               SHIFT = 3'b100, // 4
               DONE  = 3'b101; // 5

    reg [2:0] next;

    // ALWAYS BLOCK 1: Next-State Combinational Logic
    always @(*) begin
        case (state)
            IDLE : next = start ? LOAD : IDLE;
            LOAD : next = CHECK;
            CHECK: next = do_add ? ADD : SHIFT; 
            ADD  : next = SHIFT;
            SHIFT: next = last ? DONE : CHECK;  
            DONE : next = IDLE;
            default: next = IDLE;
        endcase
    end

    // ALWAYS BLOCK 2: State Register with Scan Mux
    always @(posedge clk) begin
        if (rst) begin
            state <= IDLE; 
        end 
        else begin
            state <= scan_enable ? scan_in : next;
        end
    end

    // ALWAYS BLOCK 3: Moore Output Logic
    always @(*) begin
        // Reset defaults
        load     = 1'b0;
        clear    = 1'b0;
        add_en   = 1'b0;
        shift    = 1'b0;
        count_en = 1'b0;
        done     = 1'b0;
        
        case (state)
            LOAD : begin 
                load  = 1'b1; 
                clear = 1'b1; 
            end
            ADD  : begin
                add_en = 1'b1;
            end
            SHIFT: begin 
                shift    = 1'b1; 
                count_en = 1'b1; 
            end
            DONE : begin
                done = 1'b1;
            end
            default: ; 
        endcase
    end

endmodule

week1_lab3/add_decision.v
// Student 3 — Conditional Add Logic (add_decision)
// Combinational. Inputs: Q_lsb, A, M.
// Outputs: sum = A+{1'b0,M} (always), do_add = Q_lsb.

module add_decision (
	input [8:0] A,
	input [7:0] M,
	input Q_lsb,
	output [8:0] sum,
	output do_add
);

    assign sum    = A + {1'b0, M};

    assign do_add = Q_lsb;

endmodule

week1_lab3/bit_counter.v
module ICG (
    input clk,
    input enable,
    input test_enable,
    output gated_clk
);
    reg en_latch;
    always @(clk or enable or test_enable)
        if (!clk)
            en_latch = enable | test_enable;
    assign gated_clk = clk & en_latch;
endmodule



module bit_counter (
    input clk, rst,
    input clear, count_en,
    input test_mode,
    input scan_enable,
    input [3:0] scan_in,
    output reg [3:0] count,
    output last
);

    wire gated_clk;
    ICG u_icg (
        .clk        (clk),
        .enable     (count_en),
        .test_enable(test_mode),
        .gated_clk  (gated_clk)
    );

    wire [3:0] count_next_func;
    assign count_next_func = (clear) ? 4'b0 : count + 1'b1;

    always @(posedge gated_clk) begin
        if (rst)
            count <= 4'b0;
        else
            count <= scan_enable ? scan_in : count_next_func;
    end

    assign last = (count == 4'd7);

endmodule

week1_lab3/mult_regs.v
module mult_regs(input clk, input rst, input load, input [8:0] sum, input add_en, input shift, input [7:0] a_in, input [7:0]b_in,
input scan_enable, input [8:0] scan_in_A, input [7:0] scan_in_M, input [7:0] scan_in_Q,
output reg [8:0] A, output reg [7:0] M, output reg [7:0] Q);

    always @(posedge clk)
    begin 
        if (rst) begin 
            A<=9'b0;
            M<=8'b0;
            Q<=8'b0;
        end
        else if (scan_enable) begin
            A<=scan_in_A;
            M<=scan_in_M;
            Q<=scan_in_Q;
        end 
        else if (load) begin 
            M<=a_in;
            Q<=b_in;
            A<=9'b0;
        end
        else if (add_en) A<=sum;
        else if (shift) {A,Q}<={1'b0,A,Q[7:1]};
        else
        A<=A;
    end

endmodule

week1_lab3/seq_mult.v
module seq_multiplier (
  input clk,
  input rst,
  input start,
  input [7:0] a,
  input [7:0] b,
  output [15:0] product,
  output done,
  input scan_enable,
  input test_mode,
  input scan_in,
  output scan_out
);

  wire [8:0] A;
  wire [7:0] M;
  wire [7:0] Q;
  wire [2:0] state;
  wire [8:0] sum;
  wire [3:0] count;
  wire last;
  wire do_add;
  wire load;
  wire add_en;
  wire shift;
  wire count_en;
  wire clear;

  wire [2:0] scan_state_in; //for 6 states in fsm_controller 3 flipflop
  assign scan_state_in[0] = scan_in;     //scan_in --> controller.state[2:0] 
  assign scan_state_in[1] = state[0];     // chain of flipflop
  assign scan_state_in[2] = state[1];

  wire [8:0] scan_A_in; 
  // 9 bits = 9 flipflop converting every ff to scan-ff

  //controller.state[2:0] --> mult_regs.A[8:0]

  assign scan_A_in[0] = state[2];
  assign scan_A_in[1] = A[0];
  assign scan_A_in[2] = A[1];
  assign scan_A_in[3] = A[2];
  assign scan_A_in[4] = A[3];
  assign scan_A_in[5] = A[4];
  assign scan_A_in[6] = A[5];
  assign scan_A_in[7] = A[6];
  assign scan_A_in[8] = A[7];

  wire [7:0] scan_M_in;

  //mult_regs.A[8:0] --> mult_regs.M[7:0]

  assign scan_M_in[0] = A[8];
  assign scan_M_in[1] = M[0];
  assign scan_M_in[2] = M[1];
  assign scan_M_in[3] = M[2];
  assign scan_M_in[4] = M[3];
  assign scan_M_in[5] = M[4];
  assign scan_M_in[6] = M[5];
  assign scan_M_in[7] = M[6];

  wire [7:0] scan_Q_in;

  //mult_regs.M[7:0] --> mult_regs.Q[7:0]

  assign scan_Q_in[0] = M[7];
  assign scan_Q_in[1] = Q[0];
  assign scan_Q_in[2] = Q[1];
  assign scan_Q_in[3] = Q[2];
  assign scan_Q_in[4] = Q[3];
  assign scan_Q_in[5] = Q[4];
  assign scan_Q_in[6] = Q[5];
  assign scan_Q_in[7] = Q[6];
 
  wire [3:0] scan_count_in;

  //mult_regs.Q[7:0] --> count[3:0] 

  assign scan_count_in[0] = Q[7];
  assign scan_count_in[1] = count[0];
  assign scan_count_in[2] = count[1];
  assign scan_count_in[3] = count[2];


  assign scan_out = count[3];

  //count[3:0] --> scan_out


  mult_regs U1 (
    .clk(clk),
    .rst(rst),
    .load(load),
    .add_en(add_en),
    .sum(sum),
    .shift(shift),
    .a_in(a),
    .b_in(b),
    .scan_enable(scan_enable),
    .scan_in_A(scan_A_in),
    .scan_in_M(scan_M_in),
    .scan_in_Q(scan_Q_in),
    .A(A),
    .M(M),
    .Q(Q)
  ); 

  bit_counter U2 (
    .clk(clk),
    .rst(rst),
    .clear(clear),
    .count_en(count_en),
    .scan_enable(scan_enable),
    .test_mode(test_mode),
    .scan_in(scan_count_in),
    .count(count),
    .last(last)
  );

  add_decision U3 (
    .A(A),
    .M(M),
    .Q_lsb(Q[0]),
    .sum(sum),
    .do_add(do_add)
  );

  fsm_controller U4 (
    .clk(clk),
    .rst(rst),
    .start(start),
    .last(last),
    .do_add(do_add),
    .scan_enable(scan_enable),
    .scan_in(scan_state_in),
    .state(state),
    .load(load),
    .add_en(add_en),
    .shift(shift),
    .count_en(count_en),
    .clear(clear),
    .done(done)
  );

  assign product = {A[7:0], Q};

endmodule

week1_lab3/tb_dft.v
`timescale 1ns/1ps

module tb_seq_multiplier_dft;

  reg        clk         = 0;
  reg        rst         = 1;
  reg        start       = 0;
  reg  [7:0] a, b;
  reg        test_mode   = 0;
  reg        scan_enable = 0;
  reg        scan_in     = 0;

  wire [15:0] product;
  wire        done;
  wire        scan_out;

  integer sys_clk_toggles   = 0;
  integer gated_clk_toggles = 0;
  reg     prev_gated_clk    = 0;

  seq_multiplier dut (
    .clk        (clk),
    .rst        (rst),
    .start      (start),
    .a          (a),
    .b          (b),
    .test_mode  (test_mode),
    .scan_enable(scan_enable),
    .scan_in    (scan_in),
    .product    (product),
    .done       (done),
    .scan_out   (scan_out)
  );

  always #5 clk = ~clk;

  always @(posedge clk or negedge clk)
    sys_clk_toggles = sys_clk_toggles + 1;

  wire gated_clk_monitor = dut.U2.u_icg.gated_clk;
  always @(gated_clk_monitor) begin
    if (gated_clk_monitor !== prev_gated_clk) begin
      gated_clk_toggles = gated_clk_toggles + 1;
      prev_gated_clk    = gated_clk_monitor;
    end
  end

  function [31:0] make_scan_word;
    input [2:0] f_state;
    input [8:0] f_A;
    input [7:0] f_M;
    input [7:0] f_Q;
    input [3:0] f_cnt;
    begin
      make_scan_word = {f_cnt, f_Q, f_M, f_A, f_state};
    end
  endfunction

  task do_reset;
    begin
      @(negedge clk); rst = 1;
      @(negedge clk); rst = 0;
    end
  endtask

  task test_c1_functional;
    integer toggles_idle_after;
    begin
      $display("\n========================================");
      $display("TEST C1: FUNCTIONAL TEST");
      $display("========================================");

      sys_clk_toggles   = 0;
      gated_clk_toggles = 0;
      test_mode   = 0;
      scan_enable = 0;

      @(negedge clk); rst = 0;

      repeat(5) @(negedge clk);
      $display("Clock toggles during IDLE (5 cycles):");
      $display("  System clock : %0d", sys_clk_toggles);
      $display("  Gated clock  : %0d", gated_clk_toggles);

      if (gated_clk_toggles < sys_clk_toggles / 2)
        $display("  PASS: Clock gating active in IDLE (gated_clk suppressed)");
      else
        $error("  FAIL: Clock gating not working -- gated=%0d sys=%0d",
               gated_clk_toggles, sys_clk_toggles);

      toggles_idle_after = gated_clk_toggles;

      $display("\nRunning multiplication: 13 x 11");
      @(negedge clk); a = 8'd13; b = 8'd11; start = 1;
      @(negedge clk); start = 0;
      wait(done);
      @(negedge clk);

      if (product == 16'd143)
        $display("  PASS: 13 x 11 = %0d (correct)", product);
      else
        $error("  FAIL: Expected 143, got %0d", product);

      $display("\nFinal clock toggle count:");
      $display("  System clock : %0d", sys_clk_toggles);
      $display("  Gated clock  : %0d", gated_clk_toggles);
      if (sys_clk_toggles > 0)
        $display("  Power savings: %0d%%",
                 (100*(sys_clk_toggles-gated_clk_toggles))/sys_clk_toggles);

      if (gated_clk_toggles > toggles_idle_after)
        $display("  PASS: Gated clock active during computation");
      else
        $error("  FAIL: Gated clock never toggled during multiplication");
      begin : assert1_test_mode_bypasses_icg
        integer before, after;
        @(negedge clk); test_mode = 1;
        before = gated_clk_toggles;
        repeat(4) @(negedge clk);
        after  = gated_clk_toggles;
        test_mode = 0;

        if (after > before)
          $display("  PASS [ASSERT-1]: gated_clk toggles when test_mode=1 (%0d new toggles)",
                   after - before);
        else
          $error("  FAIL [ASSERT-1]: Clock gating not bypassed");
      end
    end
  endtask
  task test_c2_scan_shift;
    reg [31:0] scan_pattern;
    integer    i;
    begin
      $display("\n========================================");
      $display("TEST C2: SCAN SHIFT TEST");
      $display("========================================");

      do_reset;
      test_mode   = 1;   
      scan_enable = 1;   
      scan_pattern = make_scan_word(3'b100, 9'h055, 8'hAA, 8'h33, 4'h5);

      $display("Shifting in 32-bit scan word: 0x%08h", scan_pattern);
      $display("  state = 3'b100 (SHIFT)");
      $display("  A     = 9'h055");
      $display("  M     = 8'hAA");
      $display("  Q     = 8'h33");
      $display("  count = 4'h5");

      for (i = 31; i >= 0; i = i - 1) begin
        @(negedge clk);
        scan_in = scan_pattern[i];
      end

      @(negedge clk); scan_enable = 0;
      #1;

      $display("\nVerifying shifted-in register values:");
      $display("  state = %b  (expected 100)", dut.U4.state);
      $display("  A     = %h  (expected 055)", dut.U1.A);
      $display("  M     = %h  (expected AA)",  dut.U1.M);
      $display("  Q     = %h  (expected 33)",  dut.U1.Q);
      $display("  count = %h  (expected 5)",   dut.U2.count);

      if (dut.U4.state === 3'b100 && dut.U1.A === 9'h055 &&
          dut.U1.M === 8'hAA     && dut.U1.Q === 8'h33 &&
          dut.U2.count === 4'h5)
        $display("  PASS: All registers contain the shifted pattern");
      else
        $error("  FAIL: Scan shift mismatch");
      begin : assert2_count_shifts_with_count_en_0

        force dut.U4.state = 3'b000;          #1;
        if (dut.U4.count_en === 1'b0 && dut.U2.count === 4'h5)
          $display("  PASS [ASSERT-2]: count=%h shifted correctly even with count_en=0 (test_mode bypassed ICG)",
                   dut.U2.count);
        else
          $error("  FAIL [ASSERT-2]: Scan shift failed (count_en=%b, count=%h)",
                 dut.U4.count_en, dut.U2.count);
        release dut.U4.state;
      end
    end
  endtask
  task test_c3_shift_capture_shift;
    reg [31:0] scan_in_pattern;
    reg [31:0] scan_out_pattern;
    reg [31:0] expected_out;
    integer    i;
    begin
      $display("\n========================================");
      $display("TEST C3: SHIFT-CAPTURE-SHIFT TEST");
      $display("========================================");

      do_reset;
      test_mode = 1;

      $display("\nSTEP 1: Shifting in test pattern (scan_enable=1)");
      scan_enable     = 1;
      scan_in_pattern = make_scan_word(3'b001, 9'h000, 8'h0D, 8'h0B, 4'h0);
      $display("  Pattern: 0x%08h", scan_in_pattern);
      $display("  state=LOAD(001), A=0, M=0x0D(13), Q=0x0B(11), count=0");

      for (i = 31; i >= 0; i = i - 1) begin
        @(negedge clk);
        scan_in = scan_in_pattern[i];
      end

      $display("\nSTEP 2: Capture cycle (scan_enable=0, one functional clock)");
      @(negedge clk); scan_enable = 0; scan_in = 0;
      @(posedge clk); 
      #1;            

      $display("  After capture: state=%b (expected CHECK=010)", dut.U4.state);

      if (dut.U4.state === 3'b010)
        $display("  PASS [ASSERT-3]: FSM transitioned correctly LOAD(001) -> CHECK(010)");
      else
        $error("  FAIL [ASSERT-3]: Functional capture failed -- state=%b, expected 010",
               dut.U4.state);
   
      $display("\nSTEP 3: Shifting out captured response (scan_enable=1)");
      scan_out_pattern = 0;
      scan_in          = 0;
      scan_enable      = 1;    

      for (i = 31; i >= 0; i = i - 1) begin
        #1;                             
        scan_out_pattern[i] = scan_out; 
        @(negedge clk); scan_in = 0;  
        @(posedge clk);                
      end

      @(negedge clk); scan_enable = 0;
      expected_out = make_scan_word(3'b010, 9'h000, 8'h0D, 8'h0B, 4'h0);

      $display("\nPattern comparison:");
      $display("  Captured : 0x%08h", scan_out_pattern);
      $display("  Expected : 0x%08h", expected_out);
      $display("  state field: captured=%b expected=010", scan_out_pattern[2:0]);
      $display("  M field    : captured=%h expected=0D",  scan_out_pattern[19:12]);
      $display("  Q field    : captured=%h expected=0B",  scan_out_pattern[27:20]);

      if (scan_out_pattern[2:0] === 3'b010)
        $display("  PASS: state field in shifted-out response is CHECK(010)");
      else
        $error("  FAIL: state field mismatch in shifted-out response (got %b)",
               scan_out_pattern[2:0]);

      if (scan_out_pattern === expected_out)
        $display("  PASS: Complete shift-capture-shift matches golden pattern");
      else
        $display("  WARN: Full pattern mismatch (see individual field checks above)");
    end
  endtask

  task test_c4_at_speed;
    reg [31:0] scan_pattern;
    integer    i;
    integer    gated_before, gated_after;
    begin
      $display("\n========================================");
      $display("TEST C4: AT-SPEED PATH TEST");
      $display("========================================");

      do_reset;
      test_mode   = 1;
      scan_enable = 1;

      scan_pattern = make_scan_word(3'b100, 9'h000, 8'h00, 8'h00, 4'h6);
      $display("Loading count=6 via scan chain (pattern: 0x%08h)", scan_pattern);

      for (i = 31; i >= 0; i = i - 1) begin
        @(negedge clk);
        scan_in = scan_pattern[i];
      end

      @(negedge clk); scan_enable = 0;
      #1;

      $display("Initial state after scan load:");
      $display("  count = %0d  (expected 6)", dut.U2.count);
      $display("  last  = %b   (expected 0)", dut.U2.last);

      if (dut.U2.count === 4'd6 && dut.U2.last === 1'b0)
        $display("  PASS: count=6, last=0 (correct initial state)");
      else
        $error("  FAIL: Initial state incorrect (count=%0d, last=%b)",
               dut.U2.count, dut.U2.last);
      $display("\nApplying one at-speed clock (SHIFT state forced, count_en=1):");
      gated_before = gated_clk_toggles;

      force dut.U4.state = 3'b100;   
      @(posedge clk);
      #1;
      release dut.U4.state;

      gated_after = gated_clk_toggles;

      $display("  count = %0d  (expected 7)", dut.U2.count);
      $display("  last  = %b   (expected 1)", dut.U2.last);

      if (dut.U2.count === 4'd7 && dut.U2.last === 1'b1)
        $display("  PASS: count=7, last=1 (at-speed timing path count->last verified)");
      else
        $error("  FAIL: At-speed increment failed (count=%0d, last=%b)",
               dut.U2.count, dut.U2.last);

      $display("\nAt-speed ICG bypass check:");
      $display("  Gated clock new toggles during forced clock: %0d",
               gated_after - gated_before);
      if ((gated_after - gated_before) >= 2)
        $display("  PASS: test_mode=1 delivered full-speed clock to counter (ICG bypassed)");
      else
        $display("  INFO: toggle count=%0d -- verify ICG test_enable path",
                 gated_after - gated_before);

      $display("  NOTE: test_mode=1 removes the clock-enable gate only;");
      $display("        propagation delay is identical to test_mode=0.");
    end
  endtask
  initial begin
    $dumpfile("seq_mult_dft.vcd");
    $dumpvars(0, tb_seq_multiplier_dft);

    $display("\n");
    $display("================================================================================");
    $display("DFT TESTBENCH: CLOCK CONTROLLABILITY AND SCAN CHAIN");
    $display("Sequential Shift-and-Add Multiplier");
    $display("================================================================================");
    $display("Instance map:  U1=mult_regs  U2=bit_counter  U3=add_decision  U4=fsm_controller");
    $display("Scan word:  [31:28]=count  [27:20]=Q  [19:12]=M  [11:3]=A  [2:0]=state");
    $display("================================================================================");

    rst = 1; #20; rst = 0; #10; rst = 1; #20;

    test_c1_functional();
    test_c2_scan_shift();
    test_c3_shift_capture_shift();
    test_c4_at_speed();

    $display("\n");
    $display("================================================================================");
    $display("ALL TESTS COMPLETE");
    $display("================================================================================");
    $display("Test C1: Functional + Power (clock gating, 13x11=143)");
    $display("Test C2: Scan Shift (32-bit pattern, correct bit layout)");
    $display("Test C3: Shift-Capture-Shift (ATPG LOAD->CHECK)");
    $display("Test C4: At-Speed Path (count=6->7, last=0->1)");
    $display("--------------------------------------------------------------------------------");
    $display("Required assertions:");
    $display("  ASSERT-1: gated_clk toggles when test_mode=1");
    $display("  ASSERT-2: count shifts when scan_enable=1 && count_en=0");
    $display("  ASSERT-3: FSM transitions correctly in capture cycle");
    $display("================================================================================");

    #100;
    $finish;
  end

  initial begin
    #200000;
    $error("TIMEOUT: Testbench did not complete");
    $finish;
  end

endmodule

week1_lab3/seq_mult_dft.vcd
$date
	Fri May 29 07:46:07 2026
$end
$version
	Icarus Verilog
$end
$timescale
	1ps
$end
$scope module tb_seq_multiplier_dft $end
$var wire 1 ! gated_clk_monitor $end
$var wire 1 " scan_out $end
$var wire 16 # product [15:0] $end
$var wire 1 $ done $end
$var reg 8 % a [7:0] $end
$var reg 8 & b [7:0] $end
$var reg 1 ' clk $end
$var reg 1 ( prev_gated_clk $end
$var reg 1 ) rst $end
$var reg 1 * scan_enable $end
$var reg 1 + scan_in $end
$var reg 1 , start $end
$var reg 1 - test_mode $end
$var integer 32 . gated_clk_toggles [31:0] $end
$var integer 32 / sys_clk_toggles [31:0] $end
$scope function make_scan_word $end
$var reg 9 0 f_A [8:0] $end
$var reg 8 1 f_M [7:0] $end
$var reg 8 2 f_Q [7:0] $end
$var reg 4 3 f_cnt [3:0] $end
$var reg 3 4 f_state [2:0] $end
$upscope $end
$scope module dut $end
$var wire 8 5 a [7:0] $end
$var wire 8 6 b [7:0] $end
$var wire 1 ' clk $end
$var wire 1 ) rst $end
$var wire 1 * scan_enable $end
$var wire 1 + scan_in $end
$var wire 1 , start $end
$var wire 1 - test_mode $end
$var wire 9 7 sum [8:0] $end
$var wire 3 8 state [2:0] $end
$var wire 1 9 shift $end
$var wire 3 : scan_state_in [2:0] $end
$var wire 1 " scan_out $end
$var wire 4 ; scan_count_in [3:0] $end
$var wire 8 < scan_Q_in [7:0] $end
$var wire 8 = scan_M_in [7:0] $end
$var wire 9 > scan_A_in [8:0] $end
$var wire 16 ? product [15:0] $end
$var wire 1 @ load $end
$var wire 1 A last $end
$var wire 1 $ done $end
$var wire 1 B do_add $end
$var wire 1 C count_en $end
$var wire 4 D count [3:0] $end
$var wire 1 E clear $end
$var wire 1 F add_en $end
$var wire 8 G Q [7:0] $end
$var wire 8 H M [7:0] $end
$var wire 9 I A [8:0] $end
$scope module U1 $end
$var wire 8 J a_in [7:0] $end
$var wire 8 K b_in [7:0] $end
$var wire 1 ' clk $end
$var wire 1 ) rst $end
$var wire 1 * scan_enable $end
$var wire 9 L scan_in_A [8:0] $end
$var wire 8 M scan_in_M [7:0] $end
$var wire 8 N scan_in_Q [7:0] $end
$var wire 9 O sum [8:0] $end
$var wire 1 9 shift $end
$var wire 1 @ load $end
$var wire 1 F add_en $end
$var reg 9 P A [8:0] $end
$var reg 8 Q M [7:0] $end
$var reg 8 R Q [7:0] $end
$upscope $end
$scope module U2 $end
$var wire 1 ' clk $end
$var wire 1 ) rst $end
$var wire 1 * scan_enable $end
$var wire 4 S scan_in [3:0] $end
$var wire 1 - test_mode $end
$var wire 1 A last $end
$var wire 1 T gated_clk $end
$var wire 4 U count_next_func [3:0] $end
$var wire 1 C count_en $end
$var wire 1 E clear $end
$var reg 4 V count [3:0] $end
$scope module u_icg $end
$var wire 1 ' clk $end
$var wire 1 T gated_clk $end
$var wire 1 - test_enable $end
$var wire 1 C enable $end
$var reg 1 W en_latch $end
$upscope $end
$upscope $end
$scope module U3 $end
$var wire 9 X A [8:0] $end
$var wire 8 Y M [7:0] $end
$var wire 1 Z Q_lsb $end
$var wire 1 B do_add $end
$var wire 9 [ sum [8:0] $end
$upscope $end
$scope module U4 $end
$var wire 1 ' clk $end
$var wire 1 B do_add $end
$var wire 1 A last $end
$var wire 1 ) rst $end
$var wire 1 * scan_enable $end
$var wire 3 \ scan_in [2:0] $end
$var wire 1 , start $end
$var parameter 3 ] ADD $end
$var parameter 3 ^ CHECK $end
$var parameter 3 _ DONE $end
$var parameter 3 ` IDLE $end
$var parameter 3 a LOAD $end
$var parameter 3 b SHIFT $end
$var reg 1 F add_en $end
$var reg 1 E clear $end
$var reg 1 C count_en $end
$var reg 1 $ done $end
$var reg 1 @ load $end
$var reg 3 c next [2:0] $end
$var reg 1 9 shift $end
$var reg 3 d state [2:0] $end
$upscope $end
$upscope $end
$scope task do_reset $end
$upscope $end
$scope task test_c1_functional $end
$var integer 32 e toggles_idle_after [31:0] $end
$scope begin assert1_test_mode_bypasses_icg $end
$var integer 32 f after [31:0] $end
$var integer 32 g before [31:0] $end
$upscope $end
$upscope $end
$scope task test_c2_scan_shift $end
$var reg 32 h scan_pattern [31:0] $end
$var integer 32 i i [31:0] $end
$scope begin assert2_count_shifts_with_count_en_0 $end
$upscope $end
$upscope $end
$scope task test_c3_shift_capture_shift $end
$var reg 32 j expected_out [31:0] $end
$var reg 32 k scan_in_pattern [31:0] $end
$var reg 32 l scan_out_pattern [31:0] $end
$var integer 32 m i [31:0] $end
$upscope $end
$scope task test_c4_at_speed $end
$var reg 32 n scan_pattern [31:0] $end
$var integer 32 o gated_after [31:0] $end
$var integer 32 p gated_before [31:0] $end
$var integer 32 q i [31:0] $end
$upscope $end
$upscope $end
$enddefinitions $end
$comment Show the parameter values. $end
$dumpall
b100 b
b1 a
b0 `
b101 _
b10 ^
b11 ]
$end
#0
$dumpvars
bx q
bx p
bx o
bx n
bx m
bx l
bx k
bx j
bx i
bx h
bx g
bx f
bx e
bx d
b0 c
bx0 \
bx [
xZ
bx Y
bx X
xW
bx V
bx U
0T
bx S
bx R
bx Q
bx P
bx O
bx N
bx M
bx L
bx K
bx J
bx I
bx H
bx G
xF
xE
bx D
xC
xB
xA
x@
bx ?
bx >
bx =
bx <
bx ;
bx0 :
x9
bx 8
bx 7
bx 6
bx 5
bx 4
bx 3
bx 2
bx 1
bx 0
b0 /
b0 .
0-
0,
0+
0*
1)
0(
0'
bx &
bx %
x$
bx #
x"
0!
$end
#5000
b1 U
0"
0B
0Z
b0 ;
b0 S
b0 <
b0 N
b0 =
b0 M
0$
0C
09
0F
0E
0@
b0 >
b0 L
b0 :
b0 \
0A
b0 D
b0 V
b0 #
b0 ?
b0 G
b0 R
b0 7
b0 O
b0 [
b0 H
b0 Q
b0 Y
b0 I
b0 P
b0 X
b0 8
b0 d
x(
b1 .
x!
xT
b1 /
1'
#10000
0(
b10 .
0!
0T
0W
b10 /
0'
#15000
b11 /
1'
#20000
b100 /
0'
0)
#25000
b101 /
1'
#30000
b110 /
0'
1)
#35000
b111 /
1'
#40000
b1000 /
0'
#45000
b1001 /
1'
#50000
0)
0'
b0 .
b1 /
#55000
b10 /
1'
#60000
b11 /
0'
#65000
b100 /
1'
#70000
b101 /
0'
#75000
b110 /
1'
#80000
b111 /
0'
#85000
b1000 /
1'
#90000
b1001 /
0'
#95000
b1010 /
1'
#100000
b0 e
b1011 /
0'
#105000
b1100 /
1'
#110000
b1 c
1,
b1011 &
b1011 6
b1011 K
b1101 %
b1101 5
b1101 J
b1101 /
0'
#115000
b0 U
1E
1@
b10 c
b10 :
b10 \
b1 8
b1 d
b1110 /
1'
#120000
0,
b1111 /
0'
#125000
b1 U
1B
1Z
b10110 <
b10110 N
b11010 =
b11010 M
0E
0@
b11 c
b100 :
b100 \
b1011 #
b1011 ?
b1011 G
b1011 R
b1101 7
b1101 O
b1101 [
b1101 H
b1101 Q
b1101 Y
b10 8
b10 d
b10000 /
1'
#130000
b10001 /
0'
#135000
1F
b100 c
b110 :
b110 \
b11 8
b11 d
b10010 /
1'
#140000
b10011 /
0'
#145000
b110100001011 #
b110100001011 ?
1C
19
0F
b10 c
b11011 >
b11011 L
b0 :
b0 \
b11010 7
b11010 O
b11010 [
b1101 I
b1101 P
b1101 X
b100 8
b100 d
b10100 /
1'
#150000
1W
b10101 /
0'
#155000
b10 U
0C
09
b11 c
b100 :
b100 \
b1100 >
b1100 L
b11 ;
b11 S
b1010 <
b1010 N
b1 D
b1 V
b10 8
b10 d
b10011 7
b10011 O
b10011 [
b110 I
b110 P
b110 X
b11010000101 #
b11010000101 ?
b10000101 G
b10000101 R
1(
b1 .
1!
1T
b10110 /
1'
#160000
0(
b10 .
0!
0T
0W
b10111 /
0'
#165000
1F
b100 c
b110 :
b110 \
b11 8
b11 d
b11000 /
1'
#170000
b11001 /
0'
#175000
1C
19
0F
b10 c
b0 :
b0 \
b1001110000101 #
b1001110000101 ?
b100111 >
b100111 L
b100 8
b100 d
b100000 7
b100000 O
b100000 [
b10011 I
b10011 P
b10011 X
b11010 /
1'
#180000
1W
b11011 /
0'
#185000
b11 U
b101 ;
b101 S
0B
0Z
b10000100 <
b10000100 N
0C
09
b100 c
b10010 >
b10010 L
b100 :
b100 \
b10 D
b10 V
b10110 7
b10110 O
b10110 [
b1001 I
b1001 P
b1001 X
b100111000010 #
b100111000010 ?
b11000010 G
b11000010 R
b10 8
b10 d
1(
b11 .
1!
1T
b11100 /
1'
#190000
0(
b100 .
0!
0T
0W
b11101 /
0'
#195000
1C
19
b10 c
b10011 >
b10011 L
b0 :
b0 \
b100 8
b100 d
b11110 /
1'
#200000
1W
b11111 /
0'
#205000
b100 U
b111 ;
b111 S
1B
1Z
b11000010 <
b11000010 N
0C
09
b11 c
b1000 >
b1000 L
b100 :
b100 \
b11 D
b11 V
b10001 7
b10001 O
b10001 [
b100 I
b100 P
b100 X
b10011100001 #
b10011100001 ?
b11100001 G
b11100001 R
b10 8
b10 d
1(
b101 .
1!
1T
b100000 /
1'
#210000
0(
b110 .
0!
0T
0W
b100001 /
0'
#215000
1F
b100 c
b110 :
b110 \
b11 8
b11 d
b100010 /
1'
#220000
b100011 /
0'
#225000
b1000111100001 #
b1000111100001 ?
1C
19
0F
b10 c
b100011 >
b100011 L
b0 :
b0 \
b11110 7
b11110 O
b11110 [
b10001 I
b10001 P
b10001 X
b100 8
b100 d
b100100 /
1'
#230000
1W
b100101 /
0'
#235000
b101 U
b1001 ;
b1001 S
0C
09
b100 c
b100 :
b100 \
b10000 >
b10000 L
0B
0Z
b11100000 <
b11100000 N
b100 D
b100 V
b10 8
b10 d
b10101 7
b10101 O
b10101 [
b1000 I
b1000 P
b1000 X
b100011110000 #
b100011110000 ?
b11110000 G
b11110000 R
1(
b111 .
1!
1T
b100110 /
1'
#240000
0(
b1000 .
0!
0T
0W
b100111 /
0'
#245000
1C
19
b10 c
b10001 >
b10001 L
b0 :
b0 \
b100 8
b100 d
b101000 /
1'
#250000
1W
b101001 /
0'
#255000
b110 U
0C
09
b100 c
b100 :
b100 \
b1000 >
b1000 L
b1010 ;
b1010 S
b11110000 <
b11110000 N
b101 D
b101 V
b10 8
b10 d
b10001 7
b10001 O
b10001 [
b100 I
b100 P
b100 X
b10001111000 #
b10001111000 ?
b1111000 G
b1111000 R
1(
b1001 .
1!
1T
b101010 /
1'
#260000
0(
b1010 .
0!
0T
0W
b101011 /
0'
#265000
1C
19
b10 c
b1001 >
b1001 L
b0 :
b0 \
b100 8
b100 d
b101100 /
1'
#270000
1W
b101101 /
0'
#275000
b111 U
b1100 ;
b1100 S
0C
09
b100 c
b100 :
b100 \
b100 >
b100 L
b1111000 <
b1111000 N
b110 D
b110 V
b10 8
b10 d
b1111 7
b1111 O
b1111 [
b10 I
b10 P
b10 X
b1000111100 #
b1000111100 ?
b111100 G
b111100 R
1(
b1011 .
1!
1T
b101110 /
1'
#280000
0(
b1100 .
0!
0T
0W
b101111 /
0'
#285000
1C
19
b10 c
b101 >
b101 L
b0 :
b0 \
b100 8
b100 d
b110000 /
1'
#290000
1W
b110001 /
0'
#295000
b1000 U
b1110 ;
b1110 S
0C
09
b100 c
b100 :
b100 \
b10 >
b10 L
b111100 <
b111100 N
1A
b111 D
b111 V
b10 8
b10 d
b1110 7
b1110 O
b1110 [
b1 I
b1 P
b1 X
b100011110 #
b100011110 ?
b11110 G
b11110 R
1(
b1101 .
1!
1T
b110010 /
1'
#300000
0(
b1110 .
0!
0T
0W
b110011 /
0'
#305000
1C
19
b101 c
b11 >
b11 L
b0 :
b0 \
b100 8
b100 d
b110100 /
1'
#310000
1W
b110101 /
0'
#315000
b1001 U
1"
1$
0C
09
b0 c
b10 :
b10 \
b1 >
b1 L
1B
1Z
b1 ;
b1 S
b11110 <
b11110 N
0A
b1000 D
b1000 V
b101 8
b101 d
b1101 7
b1101 O
b1101 [
b0 I
b0 P
b0 X
b10001111 #
b10001111 ?
b10001111 G
b10001111 R
1(
b1111 .
1!
1T
b110110 /
1'
#320000
0(
b10000 .
0!
0T
0W
b110111 /
0'
#325000
0$
b0 >
b0 L
b0 :
b0 \
b0 8
b0 d
b111000 /
1'
#330000
1W
b10000 g
1-
b111001 /
0'
